Unihandecode-0.81.dist-info/METADATA
Unihandecode-0.81.dist-info/RECORD
Unihandecode-0.81.dist-info/WHEEL
Unihandecode-0.81.dist-info/top_level.txt
unihandecode/__init__.py
unihandecode/jacodepoints.pickle.bz2
unihandecode/jadecoder.py
unihandecode/krcodepoints.pickle.bz2
unihandecode/krdecoder.py
unihandecode/unicodepoints.pickle.bz2
unihandecode/unidecoder.py
unihandecode/vncodepoints.pickle.bz2
unihandecode/vndecoder.py
unihandecode/yuecodepoints.pickle.bz2
unihandecode/zhcodepoints.pickle.bz2
unihandecode/data/UnicodeData.txt
unihandecode/data/Unihan_Readings.txt
unihandecode/gencodemap/__init__.py
unihandecode/gencodemap/unicodepoints.py
unihandecode/gencodemap/unihan_conv.py
