Metadata-Version: 2.1
Name: Unihandecode
Version: 0.81
Summary: US-ASCII transliterations of Unicode text
Home-page: https://github.com/miurahr/unihandecode/
Author: Hioshi Miura
Author-email: miurahr@linux.com
License: GPLv3/Perl
Requires-Dist: pykakasi
Requires-Dist: six
